FlugiGraphics/__init__.py
FlugiGraphics/graphics.py
flugigraphics-0.1.dist-info/METADATA
flugigraphics-0.1.dist-info/WHEEL
flugigraphics-0.1.dist-info/top_level.txt
flugigraphics-0.1.dist-info/RECORD
