Metadata-Version: 2.4
Name: FlugiGraphics
Version: 0.1
Summary: flugigraphics in python dudes
Home-page: https://github.com/itssyp/flugiGraphicsInPython
Author: Bárány Szilveszter, Domokos Kyra, Végh Ákos
Author-email: barany.szilveszter@hallgato.ppke.hu, domokos.kira@hallgato.ppke.hu, vegh.akos@hallgato.ppke.hu
Classifier: Programming Language :: Python :: 3
Classifier: License :: OSI Approved :: MIT License
Classifier: Operating System :: OS Independent
Requires-Dist: pygame
Dynamic: author
Dynamic: author-email
Dynamic: classifier
Dynamic: description-content-type
Dynamic: home-page
Dynamic: requires-dist
Dynamic: summary
